.gitignore
LICENSE
README.md
setup.py
fs_transact.egg-info/PKG-INFO
fs_transact.egg-info/SOURCES.txt
fs_transact.egg-info/dependency_links.txt
fs_transact.egg-info/entry_points.txt
fs_transact.egg-info/top_level.txt
transact/__init__.py
transact/__main__.py
transact/loopback.py
transact/makechroot.py
transact/util.py